Workbook

Sheet Overview
A1: Booking system: flows & features
A3: How to use
A4: Flows: one row per task to build. Work through it by Phase (1 -> 4).
A5: Features: every requirement we agreed, with the flows that cover it.
A6: Edit only the yellow cells: Status (dropdown) and Notes.
A7: Status values: To do, In progress, Done, Blocked. Progress below updates itself.
A8: Schema, Permissions and Insert audit tabs are reference, not tasks.
A9: Status cell looks like this: | B9: To do
A11: Progress by area
A12: Area | B12: Tasks | C12: Done | D12: In progress | E12: % done
A13: Foundation | B13: =COUNTIF(Flows!$B$2:$B$51,$A13) -> 3 | C13: =COUNTIFS(Flows!$B$2:$B$51,$A13,Flows!$K$2:$K$51,"Done") -> 0 | D13: =COUNTIFS(Flows!$B$2:$B$51,$A13,Flows!$K$2:$K$51,"In progress") -> 0 | E13: =IF(B13=0,0,C13/B13) -> 0
A14: Owner setup | B14: =COUNTIF(Flows!$B$2:$B$51,$A14) -> 5 | C14: =COUNTIFS(Flows!$B$2:$B$51,$A14,Flows!$K$2:$K$51,"Done") -> 0 | D14: =COUNTIFS(Flows!$B$2:$B$51,$A14,Flows!$K$2:$K$51,"In progress") -> 0 | E14: =IF(B14=0,0,C14/B14) -> 0
A15: Barber setup | B15: =COUNTIF(Flows!$B$2:$B$51,$A15) -> 3 | C15: =COUNTIFS(Flows!$B$2:$B$51,$A15,Flows!$K$2:$K$51,"Done") -> 0 | D15: =COUNTIFS(Flows!$B$2:$B$51,$A15,Flows!$K$2:$K$51,"In progress") -> 0 | E15: =IF(B15=0,0,C15/B15) -> 0
A16: Shifts & availability | B16: =COUNTIF(Flows!$B$2:$B$51,$A16) -> 4 | C16: =COUNTIFS(Flows!$B$2:$B$51,$A16,Flows!$K$2:$K$51,"Done") -> 0 | D16: =COUNTIFS(Flows!$B$2:$B$51,$A16,Flows!$K$2:$K$51,"In progress") -> 0 | E16: =IF(B16=0,0,C16/B16) -> 0
A17: Customer booking | B17: =COUNTIF(Flows!$B$2:$B$51,$A17) -> 6 | C17: =COUNTIFS(Flows!$B$2:$B$51,$A17,Flows!$K$2:$K$51,"Done") -> 0 | D17: =COUNTIFS(Flows!$B$2:$B$51,$A17,Flows!$K$2:$K$51,"In progress") -> 0 | E17: =IF(B17=0,0,C17/B17) -> 0
A18: Barber appointments | B18: =COUNTIF(Flows!$B$2:$B$51,$A18) -> 7 | C18: =COUNTIFS(Flows!$B$2:$B$51,$A18,Flows!$K$2:$K$51,"Done") -> 0 | D18: =COUNTIFS(Flows!$B$2:$B$51,$A18,Flows!$K$2:$K$51,"In progress") -> 0 | E18: =IF(B18=0,0,C18/B18) -> 0
A19: Emergency | B19: =COUNTIF(Flows!$B$2:$B$51,$A19) -> 2 | C19: =COUNTIFS(Flows!$B$2:$B$51,$A19,Flows!$K$2:$K$51,"Done") -> 0 | D19: =COUNTIFS(Flows!$B$2:$B$51,$A19,Flows!$K$2:$K$51,"In progress") -> 0 | E19: =IF(B19=0,0,C19/B19) -> 0
A20: Payments | B20: =COUNTIF(Flows!$B$2:$B$51,$A20) -> 2 | C20: =COUNTIFS(Flows!$B$2:$B$51,$A20,Flows!$K$2:$K$51,"Done") -> 0 | D20: =COUNTIFS(Flows!$B$2:$B$51,$A20,Flows!$K$2:$K$51,"In progress") -> 0 | E20: =IF(B20=0,0,C20/B20) -> 0
A21: In-store sales | B21: =COUNTIF(Flows!$B$2:$B$51,$A21) -> 3 | C21: =COUNTIFS(Flows!$B$2:$B$51,$A21,Flows!$K$2:$K$51,"Done") -> 0 | D21: =COUNTIFS(Flows!$B$2:$B$51,$A21,Flows!$K$2:$K$51,"In progress") -> 0 | E21: =IF(B21=0,0,C21/B21) -> 0
A22: Accounting | B22: =COUNTIF(Flows!$B$2:$B$51,$A22) -> 7 | C22: =COUNTIFS(Flows!$B$2:$B$51,$A22,Flows!$K$2:$K$51,"Done") -> 0 | D22: =COUNTIFS(Flows!$B$2:$B$51,$A22,Flows!$K$2:$K$51,"In progress") -> 0 | E22: =IF(B22=0,0,C22/B22) -> 0
A23: Rent | B23: =COUNTIF(Flows!$B$2:$B$51,$A23) -> 4 | C23: =COUNTIFS(Flows!$B$2:$B$51,$A23,Flows!$K$2:$K$51,"Done") -> 0 | D23: =COUNTIFS(Flows!$B$2:$B$51,$A23,Flows!$K$2:$K$51,"In progress") -> 0 | E23: =IF(B23=0,0,C23/B23) -> 0
A24: Scheduled jobs | B24: =COUNTIF(Flows!$B$2:$B$51,$A24) -> 2 | C24: =COUNTIFS(Flows!$B$2:$B$51,$A24,Flows!$K$2:$K$51,"Done") -> 0 | D24: =COUNTIFS(Flows!$B$2:$B$51,$A24,Flows!$K$2:$K$51,"In progress") -> 0 | E24: =IF(B24=0,0,C24/B24) -> 0
A25: Notifications | B25: =COUNTIF(Flows!$B$2:$B$51,$A25) -> 2 | C25: =COUNTIFS(Flows!$B$2:$B$51,$A25,Flows!$K$2:$K$51,"Done") -> 0 | D25: =COUNTIFS(Flows!$B$2:$B$51,$A25,Flows!$K$2:$K$51,"In progress") -> 0 | E25: =IF(B25=0,0,C25/B25) -> 0
A26: All flows | B26: =SUM(B13:B25) -> 50 | C26: =SUM(C13:C25) -> 0 | D26: =SUM(D13:D25) -> 0 | E26: =IF(B26=0,0,C26/B26) -> 0
A27: Features | B27: =COUNTA(Features!$B$2:$B$32) -> 31 | C27: =COUNTIF(Features!$E$2:$E$32,"Done") -> 0 | D27: =COUNTIF(Features!$E$2:$E$32,"In progress") -> 0 | E27: =IF(B27=0,0,C27/B27) -> 0

Sheet Flows
A1: ID | B1: Area | C1: Phase | D1: Flow / task | E1: Actor | F1: Trigger | G1: How it flows | H1: Tables touched | I1: Rules & edge cases | J1: Depends on | K1: Status | L1: Notes
A2: FND-01 | B2: Foundation | C2: 1 - Foundation | D2: Write schema + migration | E2: Dev | F2: Start of build | G2: 1. Add enums: payment_method, appointment_source, appointment_status, appointment_event_kind, appointment_payment_kind, rent_period, rent_status, rent_paid_via, barber_ledger_kind. 2. Create tables: locations, barbers, services, barber_shifts, barber_terms, rent_charges, appointments, appointment_services, appointment_events, appointment_payments, in_store_sales, barber_ledger. 3. NO changes to existing tables, columns or enums: in-store sales are marked by the in_store_sales side table; barber access comes from barbers.user_id, not user_role. Rollback: drizzle/rollback/0006_booking.down.sql. 4. Hand-written SQL: CREATE EXTENSION btree_gist; no-overlap EXCLUDE constraints on barber_shifts and appointments; CHECK constraints, including: a booked / completed / no_show appointment must have confirmed_at, and an online booking must have booking_fee > 0. | H2: All | I2: Verify PGlite (local dev) can load btree_gist before relying on it. Existing orders get channel = 'online' and satisfy the new CHECK, so no existing data changes. | J2: - | K2: To do
A3: FND-02 | B3: Foundation | C3: 1 - Foundation | D3: Barber role & login | E3: Barber | F3: Barber opens /admin/login | G3: 1. Barber enters email -> same email-OTP flow the owner uses. 2. The admin lookup becomes a staff lookup: role admin, OR a user linked from an active barbers row. 3. Session carries role + linked barber_id. 4. Admin layout shows only the barber menu for role barber. | H3: users, barbers, sessions, otp_codes | I3: A barber login with no linked barbers row sees 'ask the owner to link your profile'. Role is re-checked at code verification, as it is for admins today. | J3: FND-01 | K3: To do
A4: FND-03 | B4: Foundation | C4: 1 - Foundation | D4: Permission guards | E4: Dev | F4: Every server function | G4: 1. requireOwner() on owner-only functions: products, stock, prices, settings, locations, terms, rent, payouts, adjustments. 2. requireStaff() returns { userId, role, barberId }. 3. Barber functions always filter by the session's barberId; a barber_id sent from the browser is never trusted. | H4: - | I4: Test: barber A cannot read or change barber B's appointments, services, shifts or ledger by guessing ids. | J4: FND-02 | K4: To do
A5: OWN-01 | B5: Owner setup | C5: 1 - Foundation | D5: Manage locations | E5: Owner | F5: New branch / change | G5: 1. Create: slug, names MN/EN, address, phone, map link. 2. Edit any field. 3. Deactivate (is_active = false) instead of deleting. | H5: locations | I5: Deactivated locations disappear from online booking; existing appointments there stay valid. Delete is blocked while any appointment references it. | J5: FND-03 | K5: To do
A6: OWN-02 | B6: Owner setup | C6: 1 - Foundation | D6: Create barber & grant login | E6: Owner | F6: New barber joins | G6: 1. Create barbers row: name, slug, phone (required), photo, bio, booking fee, buffer. 2. Grant login: create or promote a users row with role barber and link barbers.user_id. 3. Set their terms (OWN-03). | H6: barbers, users, barber_terms | I6: Phone is required: customers see it on every confirmation. A barber can exist without a login; the owner then manages them. | J6: FND-02 | K6: To do
A7: OWN-03 | B7: Owner setup | C7: 3 - Money | D7: Set / change barber terms | E7: Owner (agreed with barber) | F7: Deal agreed or changed | G7: 1. Enter service cut %, product commission %, rent amount, rent period, rent start date, effective-from date. 2. Saved as a NEW row; the old row is never edited. 3. Ledger rows and rent charges created after effective-from use the new terms. | H7: barber_terms | I7: Percentages stored as basis points 0-10000 (3000 = 30%). Barbers can view their terms but never edit them. | J7: OWN-02 | K7: To do
A8: OWN-04 | B8: Owner setup | C8: 4 - Extras | D8: Deactivate barber | E8: Owner | F8: Barber leaves | G8: 1. Set is_active = false; hidden from online booking. 2. Revoke login (unlink barbers.user_id, sessions deleted). 3. Owner sees their future appointments to reassign or cancel by phone. | H8: barbers, users, sessions, appointments | I8: A barber with history can't be deleted (restrict FKs). Ledger balance and unpaid rent stay visible until settled. | J8: OWN-02 | K8: To do
A9: OWN-05 | B9: Owner setup | C9: 2 - Booking core | D9: Owner who also cuts hair | E9: Owner | F9: - | G9: 1. Link the owner's admin user to a barbers row. 2. They get owner screens plus their own barber screens. | H9: users, barbers | I9: Role stays admin; barber scoping comes from the linked barber_id, not the role. | J9: FND-03 | K9: To do
A10: BAR-01 | B10: Barber setup | C10: 2 - Booking core | D10: Edit own profile | E10: Barber | F10: Anytime | G10: 1. Edit name, bio, photo, phone, booking fee, buffer minutes. | H10: barbers | I10: Fee and buffer changes apply to NEW bookings only; existing appointments keep their frozen values. Fee 0 = no online booking; customers see 'Call to book'. | J10: FND-03 | K10: To do
A11: BAR-02 | B11: Barber setup | C11: 2 - Booking core | D11: Create a service | E11: Barber | F11: Anytime | G11: 1. Pick a location. 2. Enter name EN (required), name MN (optional), description, price, duration. 3. Save -> bookable wherever the barber has shifts at that location. | H11: services | I11: The same service at another branch is a new row with its own price ('copy to another location' helper). Duration > 0, price >= 0. The barber decides everything; the owner doesn't define service types. | J11: BAR-01 | K11: To do
A12: BAR-03 | B12: Barber setup | C12: 2 - Booking core | D12: Edit / deactivate a service | E12: Barber | F12: Price or offer changes | G12: 1. Change price, duration or name, or set inactive. | H12: services | I12: Past and upcoming appointments keep their frozen name, price and duration. Inactive services only disappear from new bookings. | J12: BAR-02 | K12: To do
A13: SHF-01 | B13: Shifts & availability | C13: 2 - Booking core | D13: Plan shifts | E13: Barber | F13: Whenever they like | G13: 1. Add a shift: location, date, from-to. Any day, any hours, no fixed weekly pattern. 2. Several shifts a day are fine (morning at A, afternoon at B). 3. Online booking opens inside these windows only. | H13: barber_shifts | I13: The database refuses overlapping shifts for the same barber (they can't be in two places at once). ends_at must be after starts_at. | J13: BAR-02 | K13: To do
... A51: NTF-02 | B51: Notifications | C51: 2 - Booking core | D51: Confirmation email - exactly once, only on confirmation | E51: System | F51: Appointment becomes confirmed (CUS-03, APT-02) | G51: 1. After the confirming transaction commits, send: date/time, location + map, barber name + phone, services, total, fee paid, due at the shop, 'call your barber to reschedule or cancel'. 2. Set confirmation_sent_at. 3. 'Resend confirmation' button for the barber / owner. | H51: appointments | I51: NEVER sent for a hold. confirmation_sent_at stops a second email when the QPay callback and the sweep both confirm. A failed send is logged and never undoes the confirmation; the resend button covers it. | J51: FND-01 | K51: To do

Sheet Features
A1: # | B1: Requirement | C1: What we decided | D1: Covered by flows | E1: Status | F1: Notes
A2: 1 | B2: Multiple locations; any barber can work at any location | C2: Barbers plan shifts per location; nothing ties a barber to one branch. | D2: OWN-01, SHF-01 | E2: To do
A3: 2 | B3: Barbers define their own services | C3: Name (EN required, MN optional), price, duration and location are all the barber's call. Same service at another branch = another row with its own price. | D3: BAR-02, BAR-03 | E3: To do
A4: 3 | B4: Several services in one appointment | C4: One barber, one location, many lines; total and duration are summed. | D4: CUS-01, APT-04 | E4: To do
A5: 4 | B5: Cleanup buffer per barber | C5: Set by the barber, frozen onto each booking. | D5: BAR-01, SHF-04 | E5: To do
A6: 5 | B6: Booking fee per barber | C6: Set by the barber, paid online, subtracted from the total at the shop, never refunded. Fee 0 = phone booking only. | D6: BAR-01, CUS-03, APT-07 | E6: To do
A7: 6 | B7: Arbitrary shifts, set by the barber | C7: Any days and hours; online booking only inside them. | D7: SHF-01, SHF-02, SHF-03 | E7: To do
A8: 7 | B8: Inside-shift bookings use slots; overtime bookings don't | C8: Availability is computed live from shifts minus appointments, so this is automatic. | D8: SHF-04, APT-02 | E8: To do
A9: 8 | B9: Bookings are confirmed ONLY by a paid fee or by the barber | C9: Online: only a paid fee confirms. Barber-entered: entering it is the confirmation. The database refuses a confirmed status without confirmed_at. | D9: CUS-03, APT-02, FND-01 | E9: To do
A10: 9 | B10: Nothing a customer submits is kept unless money arrives | C10: Before payment only a temporary hold exists; unpaid holds and unpaid QPay in-store orders are deleted. See the Insert audit tab. | D10: CUS-02, CUS-05, STO-02, JOB-01 | E10: To do
A11: 10 | B11: Confirmation email only at confirmation, exactly once | C11: Never for a hold; resend button if it fails. | D11: NTF-02 | E11: To do
A12: 11 | B12: Phone / in-person bookings with no fee, any time | C12: source = barber, fee 0; creating it is the barber's confirmation, so it's confirmed immediately. Inside or outside shifts. | D12: APT-02 | E12: To do
A13: 12 | B13: Reschedule any time, barber only; fee carries over | C13: Same appointment row; history in appointment_events. | D13: APT-03 | E13: To do
... A32: 31 | B32: Booking is purely additive to the shop | C32: Migration 0006 only creates new types and tables; rollback script restores the exact prior schema (verified). | D32: FND-01 | E32: To do

Sheet Schema
A1: Table | B1: Group | C1: Edited by | D1: Purpose | E1: Key columns | F1: Key rules
A2: locations | B2: Core | C2: Owner | D2: Branches. | E2: slug, name_mn/en, address, phone, map_link, is_active | F2: No foreign keys. Deactivate, don't delete.
A3: barbers | B3: Core | C3: Owner; barber edits own profile | D3: People who cut hair. | E3: name, phone (required), bio, photo, booking_fee, buffer_minutes, user_id | F3: user_id optional: a barber can exist without a login.
A4: services | B4: Barber's own | C4: Barber | D4: What a barber offers at one location. | E4: barber_id, location_id, name_en (req), name_mn, price, duration_minutes, is_active | F4: Same service elsewhere = another row. No shared catalog.
A5: barber_shifts | B5: Barber's own | C5: Barber | D5: Planned availability for online booking. | E5: barber_id, location_id, starts_at, ends_at | F5: No overlaps per barber (EXCLUDE). Appointments never reference shifts.
A6: barber_terms | B6: Owner's own | C6: Owner | D6: Commission and rent deal, versioned. | E6: service_cut_bps, product_commission_bps, rent_amount, rent_period, rent_starts_on, effective_from | F6: New row per change; never edited. rent_period: weekly / biweekly / monthly.
A7: rent_charges | B7: Owner's own | C7: System creates; owner confirms | D7: One row per rent due date. | E7: barber_id, amount, due_on, status, paid_via, confirmed_by | F7: Unique (barber, due_on). status: due / paid / waived; paid_via: direct / payout.
A8: appointments | B8: Booking | C8: Barber (customers only via a paid fee) | D8: One visit: barber, location, time, money. A pending row is a temporary hold. | E8: source, starts_at, ends_at, blocked_until, buffer_minutes, status (pending / booked / completed / cancelled / no_show), total, booking_fee, expires_at, confirmed_at, confirmed_by, confirmation_sent_at, needs_reschedule_at, customer name/phone/email | F8: No overlaps per barber on [starts_at, blocked_until) unless cancelled. CHECK: booked/completed/no_show need confirmed_at; online needs booking_fee > 0 and an email. Unpaid holds are deleted, not kept. Barber bookings: fee 0, no hold, confirmed on creation.
A9: appointment_services | B9: Booking | C9: Barber | D9: Lines of an appointment. | E9: service_id, name/price/duration snapshots | F9: Frozen; service edits never change them.
A10: appointment_events | B10: Booking | C10: System | D10: History: created, rescheduled, updated, flagged, cancelled, no_show, completed. | E10: kind, from_starts_at, to_starts_at, actor_id, note | F10: Append-only.
A11: appointment_payments | B11: Booking | C11: Customer (fee), barber (rest) | D11: Fee + balance payments, any method. | E11: kind, method, amount, status, qpay ids, received_by_user_id | F11: Fee paid once; balance may be split. Manual methods are paid on entry. A pending fee row is deleted with its hold.
A12: barber_ledger | B12: Accounting | C12: System + owner | D12: What the shop owes each barber, and vice versa. | E12: kind, gross_amount, rate_bps, amount, appointment_payment_id, payment_id, rent_charge_id | F12: Append-only; balance = sum(amount). Kinds: service_share, product_commission, cash_collected, rent_deduction, payout, settlement, adjustment.
... A16: users (unchanged) | B16: Shop | C16: Owner | D16: Logins. | E16: No change to user_role. | F16: A user is a barber iff an active barbers row links to them.

Sheet Permissions
A1: Action | B1: Owner | C1: Barber | D1: Customer
A2: Products, prices, stock, settings | B2: Edit | C2: - | D2: -
A3: Locations | B3: Edit | C3: View | D3: View
A4: Barber terms (commission %, rent) | B4: Edit | C4: View own | D4: -
A5: Rent charges: confirm / waive | B5: Yes | C5: View own | D5: -
A6: Payouts, cash hand-ins, adjustments | B6: Yes | C6: View own | D6: -
A7: Own profile, fee, buffer, phone | B7: Edit anyone's | C7: Edit own | D7: -
A8: Services | B8: Edit anyone's | C8: Edit own | D8: View active
A9: Shifts | B9: Edit anyone's | C9: Edit own | D9: -
A10: Book online inside shifts | B10: - | C10: - | D10: Yes
A11: Create booking any time (phone / in person) | B11: Yes | C11: Own only | D11: -
A12: Reschedule / cancel / no-show / complete | B12: Yes | C12: Own only | D12: Call the barber
... A16: Earnings / ledger | B16: All barbers | C16: Own only | D16: -

Sheet Insert audit
A1: Flow | B1: What gets inserted | C1: Triggered by | D1: Money first? | E1: Verdict | F1: Why
A2: CUS-01 Browse | B2: Nothing | C2: Customer (public) | D2: - | E2: OK | F2: Read only.
A3: CUS-02 Hold the slot | B3: Pending appointment + its lines + pending fee payment | C3: Customer (public) | D3: No (temporary) | E3: Allowed, temporary | F3: The only pre-payment insert. Needed so two people can't pay for one slot. Deleted if unpaid (CUS-05). No events, emails, ledger or attempts log.
A4: CUS-03 Fee paid | B4: Booking confirmed, event, ledger rows | C4: QPay payment | D4: Yes | E4: Behind money | F4: Everything durable about an online booking is written here.
A5: CUS-05 / JOB-01 Sweep | B5: Deletes unpaid holds and unpaid QPay in-store orders | C5: System | D5: - | E5: Cleanup | F5: Unpaid attempts leave no trace.
A6: Removed: online request without a fee | B6: Pending appointment waiting for the barber | C6: Customer (public) | D6: No | E6: REMOVED | F6: A public insert with no money behind it. No-fee barbers are phone-only now; the barber enters those bookings (APT-02).
A7: APT-02 Barber-entered booking | B7: Appointment + lines + event | C7: Barber (logged in) | D7: No | E7: Allowed, on purpose | F7: The barber vouches for a phone / in-person customer. Accountable login, scoped to their own calendar.
A8: APT-03..06, EMG-01/02 | B8: Updates + appointment_events | C8: Barber (logged in) | D8: No | E8: Allowed | F8: Changes to bookings that already exist; events are the audit trail.
A9: APT-07, PAY-01/02 Checkout | B9: Payments + ledger rows | C9: Barber (logged in) | D9: Is the money | E9: Behind money | F9: QPay rows confirm via QPay; cash / POS / transfer rows are the barber's record of money received.
A10: STO-01 Build a sale | B10: Nothing | C10: Barber (logged in) | D10: - | E10: OK | F10: Built on screen only.
A11: STO-02 Take payment | B11: Order + items + payment | C11: Barber (logged in) | D11: Yes (cash/POS/transfer); temporary hold (QPay) | E11: Behind money | F11: Order is written with its first payment. Unpaid QPay hold deleted by the sweep.
A12: OWN-*, BAR-*, SHF-* Setup | B12: Locations, barbers, services, shifts, terms | C12: Owner / barber (logged in) | D12: No | E12: Allowed | F12: Configuration by staff, not customer data; a payment gate makes no sense here.
... A18: Existing shop checkout (not in these flows) | B18: orders kept as 'expired' when unpaid + a checkout_attempts row per attempt | C18: Customer (public) | D18: No | E18: Breaks the rule today | F18: Open question: apply the same delete-if-unpaid rule to the online shop?
